st_openai_embeddings_connection/__init__.py
st_openai_embeddings_connection/connection.py
st_openai_embeddings_connection-0.1.1.dist-info/LICENSE
st_openai_embeddings_connection-0.1.1.dist-info/METADATA
st_openai_embeddings_connection-0.1.1.dist-info/WHEEL
st_openai_embeddings_connection-0.1.1.dist-info/top_level.txt
st_openai_embeddings_connection-0.1.1.dist-info/RECORD
