Metadata-Version: 2.1
Name: st-openai-embeddings-connection
Version: 0.1.1
Summary: A Python package for connecting to OpenAI embedding models in Streamlit apps
Author-email: Gerard Bentley <gerardrbentley@gmail.com>
License: MIT
Requires-Python: >=3.8.0
License-File: LICENSE
Requires-Dist: streamlit (>=1.22.0)
